{
  "main": {
    "id": "69e7d69f9ab0b438",
    "type": "split",
    "children": [
      {
        "id": "a80567cf6bf8c61b",
        "type": "tabs",
        "children": [
          {
            "id": "e4b785b913d02f72",
            "type": "leaf",
            "state": {
              "type": "markdown",
              "state": {
                "file": "knowledge/INDEX.md",
                "mode": "source",
                "source": false
              },
              "icon": "lucide-file",
              "title": "INDEX"
            }
          }
        ]
      }
    ],
    "direction": "vertical"
  },
  "left": {
    "id": "b638e689cacc57e9",
    "type": "split",
    "children": [
      {
        "id": "f7a03fa3bcd00b14",
        "type": "tabs",
        "children": [
          {
            "id": "3afcbb5720da978c",
            "type": "leaf",
            "state": {
              "type": "file-explorer",
              "state": {
                "sortOrder": "alphabetical",
                "autoReveal": false
              },
              "icon": "lucide-folder-closed",
              "title": "Файловый менеджер"
            }
          },
          {
            "id": "49c7005055f8039a",
            "type": "leaf",
            "state": {
              "type": "search",
              "state": {
                "query": "",
                "matchingCase": false,
                "explainSearch": false,
                "collapseAll": false,
                "extraContext": false,
                "sortOrder": "alphabetical"
              },
              "icon": "lucide-search",
              "title": "Поиск"
            }
          },
          {
            "id": "2e88ca9cf81b28dc",
            "type": "leaf",
            "state": {
              "type": "bookmarks",
              "state": {},
              "icon": "lucide-bookmark",
              "title": "Закладки"
            }
          }
        ]
      }
    ],
    "direction": "horizontal",
    "width": 300
  },
  "right": {
    "id": "ac7ab90b1eba0822",
    "type": "split",
    "children": [
      {
        "id": "b556198653b97663",
        "type": "tabs",
        "children": [
          {
            "id": "37f064d012c460da",
            "type": "leaf",
            "state": {
              "type": "backlink",
              "state": {
                "file": "knowledge/INDEX.md",
                "collapseAll": false,
                "extraContext": false,
                "sortOrder": "alphabetical",
                "showSearch": false,
                "searchQuery": "",
                "backlinkCollapsed": false,
                "unlinkedCollapsed": true
              },
              "icon": "links-coming-in",
              "title": "Обратные ссылки для INDEX"
            }
          },
          {
            "id": "cec39e197ef2c20a",
            "type": "leaf",
            "state": {
              "type": "outgoing-link",
              "state": {
                "file": "knowledge/INDEX.md",
                "linksCollapsed": false,
                "unlinkedCollapsed": true
              },
              "icon": "links-going-out",
              "title": "Исходящие ссылки из INDEX"
            }
          },
          {
            "id": "84f7ed10022df3fb",
            "type": "leaf",
            "state": {
              "type": "tag",
              "state": {
                "sortOrder": "frequency",
                "useHierarchy": true,
                "showSearch": false,
                "searchQuery": ""
              },
              "icon": "lucide-tags",
              "title": "Теги"
            }
          },
          {
            "id": "d129b170db22ffc2",
            "type": "leaf",
            "state": {
              "type": "all-properties",
              "state": {
                "sortOrder": "frequency",
                "showSearch": false,
                "searchQuery": ""
              },
              "icon": "lucide-archive",
              "title": "Все свойства"
            }
          },
          {
            "id": "83f5578facfcabe0",
            "type": "leaf",
            "state": {
              "type": "outline",
              "state": {
                "file": "knowledge/INDEX.md",
                "followCursor": false,
                "showSearch": false,
                "searchQuery": ""
              },
              "icon": "lucide-list",
              "title": "Структура INDEX"
            }
          }
        ]
      }
    ],
    "direction": "horizontal",
    "width": 300,
    "collapsed": true
  },
  "left-ribbon": {
    "hiddenItems": {
      "switcher:Меню быстрого перехода": false,
      "graph:Граф": false,
      "canvas:Создать новый холст": false,
      "daily-notes:Сегодняшняя заметка": false,
      "templates:Вставить шаблон": false,
      "command-palette:Открыть палитру команд": false,
      "bases:Создать новую базу": false
    }
  },
  "active": "3afcbb5720da978c",
  "lastOpenFiles": [
    "applications/enterprise/api/__pycache__/register.cpython-314.pyc",
    "applications/enterprise/api/__pycache__/middleware.cpython-314.pyc",
    "applications/enterprise/api/__pycache__/handlers.cpython-314.pyc",
    "applications/enterprise/api/__pycache__/__init__.cpython-314.pyc",
    "applications/enterprise/api/__pycache__",
    "applications/enterprise/shared/__pycache__/store.cpython-314.pyc",
    "applications/enterprise/shared/__pycache__/exceptions.cpython-314.pyc",
    "applications/enterprise/shared/__pycache__/__init__.cpython-314.pyc",
    "applications/enterprise/shared/__pycache__",
    "applications/enterprise/__pycache__/services.cpython-314.pyc",
    "applications/enterprise/__pycache__/platform.cpython-314.pyc",
    "knowledge/applications/ENTERPRISE.md",
    "docs/ENTERPRISE_AI.md",
    "docs/COMPLIANCE.md",
    "docs/ADMINISTRATION.md",
    "docs/ORGANIZATION.md",
    "docs/ENTERPRISE.md",
    "knowledge/applications/AI_OS.md",
    "docs/AI_RUNTIME.md",
    "docs/SYSTEM_BUS.md",
    "docs/AI_KERNEL.md",
    "docs/AI_OS.md",
    "knowledge/applications/EXECUTIVE_CENTER.md",
    "docs/SYSTEM_MONITORING.md",
    "docs/EXECUTIVE_DASHBOARD.md",
    "docs/EXECUTIVE_CENTER.md",
    "knowledge/applications/WORKFLOW_STUDIO.md",
    "docs/WORKFLOW_REFERENCE.md",
    "docs/VISUAL_AUTOMATION.md",
    "docs/FLOW_BUILDER.md",
    "docs/WORKFLOW_STUDIO.md",
    "knowledge/applications/MARKETPLACE.md",
    "docs/PACKAGE_MANAGER.md",
    "docs/DEVELOPER_PORTAL.md",
    "docs/PLUGIN_STORE.md",
    "docs/MARKETPLACE.md",
    "knowledge/canvas/ENTERPRISE_ARCHITECTURE.canvas"
  ]
}